keyclock_dhruvanshu1775/__init__.py
keyclock_dhruvanshu1775-0.0.2.dist-info/METADATA
keyclock_dhruvanshu1775-0.0.2.dist-info/WHEEL
keyclock_dhruvanshu1775-0.0.2.dist-info/top_level.txt
keyclock_dhruvanshu1775-0.0.2.dist-info/RECORD
