Metadata-Version: 2.1
Name: keyclock-dhruvanshu1775
Version: 0.0.2
Summary: A very basic app
Home-page: UNKNOWN
Author: dhruv p
Author-email: dhruvanshu.p@latitudetechnolabs.com
License: MIT
Keywords: mykeyclock
Platform: UNKNOWN
Classifier: Development Status :: 5 - Production/Stable
Classifier: Intended Audience :: Education
Classifier: Operating System :: Microsoft :: Windows :: Windows 10
Classifier: License :: OSI Approved :: MIT License
Classifier: Programming Language :: Python :: 3
